diff_surfel_rasterization/__init__.py
diff_surfel_rasterization/csrc/ext.cpp
diff_surfel_rasterization/csrc/rasterize_points.cu
diff_surfel_rasterization/csrc/rasterize_points.h
diff_surfel_rasterization/csrc/cuda_rasterizer/auxiliary.h
diff_surfel_rasterization/csrc/cuda_rasterizer/backward.cu
diff_surfel_rasterization/csrc/cuda_rasterizer/backward.h
diff_surfel_rasterization/csrc/cuda_rasterizer/config.h
diff_surfel_rasterization/csrc/cuda_rasterizer/forward.cu
diff_surfel_rasterization/csrc/cuda_rasterizer/forward.h
diff_surfel_rasterization/csrc/cuda_rasterizer/rasterizer.h
diff_surfel_rasterization/csrc/cuda_rasterizer/rasterizer_impl.cu
diff_surfel_rasterization/csrc/cuda_rasterizer/rasterizer_impl.h
diff_surfel_rasterization/third_party/glm/.appveyor.yml
diff_surfel_rasterization/third_party/glm/.git
diff_surfel_rasterization/third_party/glm/.gitignore
diff_surfel_rasterization/third_party/glm/.travis.yml
diff_surfel_rasterization/third_party/glm/CMakeLists.txt
diff_surfel_rasterization/third_party/glm/copying.txt
diff_surfel_rasterization/third_party/glm/manual.md
diff_surfel_rasterization/third_party/glm/readme.md
diff_surfel_rasterization/third_party/glm/cmake/cmake_uninstall.cmake.in
diff_surfel_rasterization/third_party/glm/doc/man.doxy
diff_surfel_rasterization/third_party/glm/doc/manual.pdf
diff_surfel_rasterization/third_party/glm/doc/api/a00001_source.html
diff_surfel_rasterization/third_party/glm/doc/api/a00002_source.html
diff_surfel_rasterization/third_party/glm/doc/api/a00003_source.html
diff_surfel_rasterization/third_party/glm/doc/api/a00004_source.html
diff_surfel_rasterization/third_party/glm/doc/api/a00005_source.html
diff_surfel_rasterization/third_party/glm/doc/api/a00006_source.html
diff_surfel_rasterization/third_party/glm/doc/api/a00007.html
diff_surfel_rasterization/third_party/glm/doc/api/a00007_source.html
diff_surfel_rasterization/third_party/glm/doc/api/a00008.html
eden_diff_surfel_rasterization-0.1.0b0.dist-info/licenses/LICENSE.md
eden_diff_surfel_rasterization-0.1.0b0.dist-info/METADATA
eden_diff_surfel_rasterization-0.1.0b0.dist-info/WHEEL
eden_diff_surfel_rasterization-0.1.0b0.dist-info/top_level.txt
eden_diff_surfel_rasterization-0.1.0b0.dist-info/RECORD
