Metadata-Version: 2.4
Name: eden_diff_surfel_rasterization
Version: 0.1.0b0
Summary: Differentiable rasterizer for 2D Gaussian Splatting
Home-page: https://github.com/Kashu7100/diff-surfel-rasterization
Author: Kashu Yamazaki
Requires-Python: >=3.7
License-File: LICENSE.md
Requires-Dist: torch>=1.13.0
Requires-Dist: ninja
Dynamic: author
Dynamic: description
Dynamic: description-content-type
Dynamic: home-page
Dynamic: license-file
Dynamic: requires-dist
Dynamic: requires-python
Dynamic: summary
